README.txt
buildout.cfg
setup.py
src/zc/__init__.py
src/zc.zkzopeserver.egg-info/PKG-INFO
src/zc.zkzopeserver.egg-info/SOURCES.txt
src/zc.zkzopeserver.egg-info/dependency_links.txt
src/zc.zkzopeserver.egg-info/entry_points.txt
src/zc.zkzopeserver.egg-info/namespace_packages.txt
src/zc.zkzopeserver.egg-info/not-zip-safe
src/zc.zkzopeserver.egg-info/requires.txt
src/zc.zkzopeserver.egg-info/top_level.txt
src/zc/zkzopeserver/README.txt
src/zc/zkzopeserver/__init__.py
src/zc/zkzopeserver/tests.py