Metadata-Version: 1.0
Name: zc.zkzopeserver
Version: 0.3.0
Summary: zope.server wrapper that registers with ZooKeeper
Home-page: UNKNOWN
Author: Jim Fulton
Author-email: jim@zope.com
License: ZPL 2.1
Platform: UNKNOWN
